<annotation>
   <path>./data\Town01\rgb0\611.jpg</path>
   <bbox_num>2</bbox_num>
   <size>
       <width>1080</width>
       <height>1080</height>
       <depth>3</depth>
   </size>
   <object>
       <name>TrafficSign</name>
       <label_id>1</label_id>
       <bndbox>
           <xmin>619</xmin>
           <ymin>525</ymin>
           <xmax>643</xmax>
           <ymax>549</ymax>
       </bndbox>
   </object>
   <object>
       <name>Vehicle</name>
       <label_id>2</label_id>
       <bndbox>
           <xmin>509</xmin>
           <ymin>555</ymin>
           <xmax>569</xmax>
           <ymax>595</ymax>
       </bndbox>
   </object>
</annotation>
