<annotation>
   <path>./data\Town02\rgb0\376.jpg</path>
   <bbox_num>3</bbox_num>
   <size>
       <width>1080</width>
       <height>1080</height>
       <depth>3</depth>
   </size>
   <object>
       <name>TrafficLight</name>
       <label_id>0</label_id>
       <bndbox>
           <xmin>133</xmin>
           <ymin>477</ymin>
           <xmax>151</xmax>
           <ymax>531</ymax>
       </bndbox>
   </object>
   <object>
       <name>TrafficSign</name>
       <label_id>1</label_id>
       <bndbox>
           <xmin>719</xmin>
           <ymin>505</ymin>
           <xmax>775</xmax>
           <ymax>559</ymax>
       </bndbox>
   </object>
   <object>
       <name>Vehicle</name>
       <label_id>2</label_id>
       <bndbox>
           <xmin>525</xmin>
           <ymin>553</ymin>
           <xmax>555</xmax>
           <ymax>573</ymax>
       </bndbox>
   </object>
</annotation>
