<annotation>
   <path>./data\Town03\rgb0\919.jpg</path>
   <bbox_num>5</bbox_num>
   <size>
       <width>1080</width>
       <height>1080</height>
       <depth>3</depth>
   </size>
   <object>
       <name>TrafficLight</name>
       <label_id>0</label_id>
       <bndbox>
           <xmin>555</xmin>
           <ymin>417</ymin>
           <xmax>563</xmax>
           <ymax>449</ymax>
       </bndbox>
   </object>
   <object>
       <name>TrafficLight</name>
       <label_id>0</label_id>
       <bndbox>
           <xmin>701</xmin>
           <ymin>409</ymin>
           <xmax>709</xmax>
           <ymax>445</ymax>
       </bndbox>
   </object>
   <object>
       <name>TrafficLight</name>
       <label_id>0</label_id>
       <bndbox>
           <xmin>837</xmin>
           <ymin>401</ymin>
           <xmax>851</xmax>
           <ymax>439</ymax>
       </bndbox>
   </object>
   <object>
       <name>Roadline</name>
       <label_id>4</label_id>
       <bndbox>
           <xmin>905</xmin>
           <ymin>693</ymin>
           <xmax>1080</xmax>
           <ymax>707</ymax>
       </bndbox>
   </object>
   <object>
       <name>Roadline</name>
       <label_id>4</label_id>
       <bndbox>
           <xmin>654</xmin>
           <ymin>677</ymin>
           <xmax>841</xmax>
           <ymax>691</ymax>
       </bndbox>
   </object>
</annotation>
