<annotation>
   <path>./data\Town05\rgb0\405.jpg</path>
   <bbox_num>10</bbox_num>
   <size>
       <width>1080</width>
       <height>1080</height>
       <depth>3</depth>
   </size>
   <object>
       <name>TrafficLight</name>
       <label_id>0</label_id>
       <bndbox>
           <xmin>819</xmin>
           <ymin>409</ymin>
           <xmax>829</xmax>
           <ymax>433</ymax>
       </bndbox>
   </object>
   <object>
       <name>TrafficLight</name>
       <label_id>0</label_id>
       <bndbox>
           <xmin>863</xmin>
           <ymin>389</ymin>
           <xmax>875</xmax>
           <ymax>417</ymax>
       </bndbox>
   </object>
   <object>
       <name>TrafficLight</name>
       <label_id>0</label_id>
       <bndbox>
           <xmin>936</xmin>
           <ymin>353</ymin>
           <xmax>953</xmax>
           <ymax>389</ymax>
       </bndbox>
   </object>
   <object>
       <name>TrafficLight</name>
       <label_id>0</label_id>
       <bndbox>
           <xmin>69</xmin>
           <ymin>265</ymin>
           <xmax>95</xmax>
           <ymax>317</ymax>
       </bndbox>
   </object>
   <object>
       <name>TrafficLight</name>
       <label_id>0</label_id>
       <bndbox>
           <xmin>259</xmin>
           <ymin>261</ymin>
           <xmax>281</xmax>
           <ymax>317</ymax>
       </bndbox>
   </object>
   <object>
       <name>TrafficLight</name>
       <label_id>0</label_id>
       <bndbox>
           <xmin>419</xmin>
           <ymin>259</ymin>
           <xmax>435</xmax>
           <ymax>317</ymax>
       </bndbox>
   </object>
   <object>
       <name>Vehicle</name>
       <label_id>2</label_id>
       <bndbox>
           <xmin>767</xmin>
           <ymin>559</ymin>
           <xmax>951</xmax>
           <ymax>601</ymax>
       </bndbox>
   </object>
   <object>
       <name>Roadline</name>
       <label_id>4</label_id>
       <bndbox>
           <xmin>795</xmin>
           <ymin>823</ymin>
           <xmax>989</xmax>
           <ymax>1015</ymax>
       </bndbox>
   </object>
   <object>
       <name>Roadline</name>
       <label_id>4</label_id>
       <bndbox>
           <xmin>0</xmin>
           <ymin>691</ymin>
           <xmax>1007</xmax>
           <ymax>763</ymax>
       </bndbox>
   </object>
   <object>
       <name>Roadline</name>
       <label_id>4</label_id>
       <bndbox>
           <xmin>687</xmin>
           <ymin>651</ymin>
           <xmax>903</xmax>
           <ymax>653</ymax>
       </bndbox>
   </object>
</annotation>
