<annotation>
   <path>./data\Town05\rgb0\764.jpg</path>
   <bbox_num>5</bbox_num>
   <size>
       <width>1080</width>
       <height>1080</height>
       <depth>3</depth>
   </size>
   <object>
       <name>Vehicle</name>
       <label_id>2</label_id>
       <bndbox>
           <xmin>85</xmin>
           <ymin>547</ymin>
           <xmax>165</xmax>
           <ymax>567</ymax>
       </bndbox>
   </object>
   <object>
       <name>Vehicle</name>
       <label_id>2</label_id>
       <bndbox>
           <xmin>207</xmin>
           <ymin>541</ymin>
           <xmax>289</xmax>
           <ymax>563</ymax>
       </bndbox>
   </object>
   <object>
       <name>Roadline</name>
       <label_id>4</label_id>
       <bndbox>
           <xmin>785</xmin>
           <ymin>809</ymin>
           <xmax>955</xmax>
           <ymax>977</ymax>
       </bndbox>
   </object>
   <object>
       <name>Roadline</name>
       <label_id>4</label_id>
       <bndbox>
           <xmin>0</xmin>
           <ymin>693</ymin>
           <xmax>393</xmax>
           <ymax>1080</ymax>
       </bndbox>
   </object>
   <object>
       <name>Roadline</name>
       <label_id>4</label_id>
       <bndbox>
           <xmin>70</xmin>
           <ymin>673</ymin>
           <xmax>429</xmax>
           <ymax>1080</ymax>
       </bndbox>
   </object>
</annotation>
