<annotation>
   <path>./data\Town10\rgb0\1543.jpg</path>
   <bbox_num>4</bbox_num>
   <size>
       <width>1080</width>
       <height>1080</height>
       <depth>3</depth>
   </size>
   <object>
       <name>TrafficSign</name>
       <label_id>1</label_id>
       <bndbox>
           <xmin>819</xmin>
           <ymin>487</ymin>
           <xmax>833</xmax>
           <ymax>517</ymax>
       </bndbox>
   </object>
   <object>
       <name>Vehicle</name>
       <label_id>2</label_id>
       <bndbox>
           <xmin>355</xmin>
           <ymin>541</ymin>
           <xmax>391</xmax>
           <ymax>575</ymax>
       </bndbox>
   </object>
   <object>
       <name>Roadline</name>
       <label_id>4</label_id>
       <bndbox>
           <xmin>15</xmin>
           <ymin>703</ymin>
           <xmax>333</xmax>
           <ymax>1080</ymax>
       </bndbox>
   </object>
   <object>
       <name>Roadline</name>
       <label_id>4</label_id>
       <bndbox>
           <xmin>87</xmin>
           <ymin>643</ymin>
           <xmax>379</xmax>
           <ymax>1080</ymax>
       </bndbox>
   </object>
</annotation>
