<annotation>
   <path>./data\Town10\rgb0\1555.jpg</path>
   <bbox_num>4</bbox_num>
   <size>
       <width>1080</width>
       <height>1080</height>
       <depth>3</depth>
   </size>
   <object>
       <name>Vehicle</name>
       <label_id>2</label_id>
       <bndbox>
           <xmin>427</xmin>
           <ymin>549</ymin>
           <xmax>453</xmax>
           <ymax>563</ymax>
       </bndbox>
   </object>
   <object>
       <name>Vehicle</name>
       <label_id>2</label_id>
       <bndbox>
           <xmin>391</xmin>
           <ymin>543</ymin>
           <xmax>423</xmax>
           <ymax>573</ymax>
       </bndbox>
   </object>
   <object>
       <name>Roadline</name>
       <label_id>4</label_id>
       <bndbox>
           <xmin>7</xmin>
           <ymin>699</ymin>
           <xmax>331</xmax>
           <ymax>1080</ymax>
       </bndbox>
   </object>
   <object>
       <name>Roadline</name>
       <label_id>4</label_id>
       <bndbox>
           <xmin>79</xmin>
           <ymin>640</ymin>
           <xmax>375</xmax>
           <ymax>1080</ymax>
       </bndbox>
   </object>
</annotation>
