<annotation>
   <path>./data\Town10\rgb0\598.jpg</path>
   <bbox_num>13</bbox_num>
   <size>
       <width>1080</width>
       <height>1080</height>
       <depth>3</depth>
   </size>
   <object>
       <name>TrafficLight</name>
       <label_id>0</label_id>
       <bndbox>
           <xmin>209</xmin>
           <ymin>489</ymin>
           <xmax>219</xmax>
           <ymax>511</ymax>
       </bndbox>
   </object>
   <object>
       <name>TrafficLight</name>
       <label_id>0</label_id>
       <bndbox>
           <xmin>715</xmin>
           <ymin>447</ymin>
           <xmax>735</xmax>
           <ymax>491</ymax>
       </bndbox>
   </object>
   <object>
       <name>TrafficLight</name>
       <label_id>0</label_id>
       <bndbox>
           <xmin>521</xmin>
           <ymin>411</ymin>
           <xmax>531</xmax>
           <ymax>449</ymax>
       </bndbox>
   </object>
   <object>
       <name>TrafficLight</name>
       <label_id>0</label_id>
       <bndbox>
           <xmin>391</xmin>
           <ymin>411</ymin>
           <xmax>401</xmax>
           <ymax>447</ymax>
       </bndbox>
   </object>
   <object>
       <name>TrafficSign</name>
       <label_id>1</label_id>
       <bndbox>
           <xmin>569</xmin>
           <ymin>419</ymin>
           <xmax>583</xmax>
           <ymax>443</ymax>
       </bndbox>
   </object>
   <object>
       <name>TrafficSign</name>
       <label_id>1</label_id>
       <bndbox>
           <xmin>903</xmin>
           <ymin>417</ymin>
           <xmax>929</xmax>
           <ymax>477</ymax>
       </bndbox>
   </object>
   <object>
       <name>TrafficSign</name>
       <label_id>1</label_id>
       <bndbox>
           <xmin>701</xmin>
           <ymin>405</ymin>
           <xmax>717</xmax>
           <ymax>417</ymax>
       </bndbox>
   </object>
   <object>
       <name>Vehicle</name>
       <label_id>2</label_id>
       <bndbox>
           <xmin>525</xmin>
           <ymin>544</ymin>
           <xmax>555</xmax>
           <ymax>575</ymax>
       </bndbox>
   </object>
   <object>
       <name>Roadline</name>
       <label_id>4</label_id>
       <bndbox>
           <xmin>0</xmin>
           <ymin>951</ymin>
           <xmax>81</xmax>
           <ymax>1026</ymax>
       </bndbox>
   </object>
   <object>
       <name>Roadline</name>
       <label_id>4</label_id>
       <bndbox>
           <xmin>94</xmin>
           <ymin>949</ymin>
           <xmax>303</xmax>
           <ymax>1080</ymax>
       </bndbox>
   </object>
   <object>
       <name>Roadline</name>
       <label_id>4</label_id>
       <bndbox>
           <xmin>381</xmin>
           <ymin>947</ymin>
           <xmax>523</xmax>
           <ymax>1080</ymax>
       </bndbox>
   </object>
   <object>
       <name>Roadline</name>
       <label_id>4</label_id>
       <bndbox>
           <xmin>637</xmin>
           <ymin>945</ymin>
           <xmax>807</xmax>
           <ymax>1080</ymax>
       </bndbox>
   </object>
   <object>
       <name>Roadline</name>
       <label_id>4</label_id>
       <bndbox>
           <xmin>853</xmin>
           <ymin>943</ymin>
           <xmax>1080</xmax>
           <ymax>1080</ymax>
       </bndbox>
   </object>
</annotation>
