<annotation>
   <path>./data\Town10\rgb0\730.jpg</path>
   <bbox_num>4</bbox_num>
   <size>
       <width>1080</width>
       <height>1080</height>
       <depth>3</depth>
   </size>
   <object>
       <name>Vehicle</name>
       <label_id>2</label_id>
       <bndbox>
           <xmin>139</xmin>
           <ymin>551</ymin>
           <xmax>167</xmax>
           <ymax>569</ymax>
       </bndbox>
   </object>
   <object>
       <name>Vehicle</name>
       <label_id>2</label_id>
       <bndbox>
           <xmin>171</xmin>
           <ymin>541</ymin>
           <xmax>227</xmax>
           <ymax>580</ymax>
       </bndbox>
   </object>
   <object>
       <name>Roadline</name>
       <label_id>4</label_id>
       <bndbox>
           <xmin>658</xmin>
           <ymin>721</ymin>
           <xmax>1080</xmax>
           <ymax>1080</ymax>
       </bndbox>
   </object>
   <object>
       <name>Roadline</name>
       <label_id>4</label_id>
       <bndbox>
           <xmin>305</xmin>
           <ymin>685</ymin>
           <xmax>337</xmax>
           <ymax>739</ymax>
       </bndbox>
   </object>
</annotation>
