<annotation>
   <path>./data\Town10\rgb0\801.jpg</path>
   <bbox_num>7</bbox_num>
   <size>
       <width>1080</width>
       <height>1080</height>
       <depth>3</depth>
   </size>
   <object>
       <name>TrafficSign</name>
       <label_id>1</label_id>
       <bndbox>
           <xmin>687</xmin>
           <ymin>499</ymin>
           <xmax>699</xmax>
           <ymax>531</ymax>
       </bndbox>
   </object>
   <object>
       <name>Vehicle</name>
       <label_id>2</label_id>
       <bndbox>
           <xmin>406</xmin>
           <ymin>551</ymin>
           <xmax>429</xmax>
           <ymax>563</ymax>
       </bndbox>
   </object>
   <object>
       <name>Vehicle</name>
       <label_id>2</label_id>
       <bndbox>
           <xmin>343</xmin>
           <ymin>541</ymin>
           <xmax>377</xmax>
           <ymax>575</ymax>
       </bndbox>
   </object>
   <object>
       <name>Rider</name>
       <label_id>3</label_id>
       <bndbox>
           <xmin>209</xmin>
           <ymin>555</ymin>
           <xmax>249</xmax>
           <ymax>635</ymax>
       </bndbox>
   </object>
   <object>
       <name>Rider</name>
       <label_id>3</label_id>
       <bndbox>
           <xmin>77</xmin>
           <ymin>555</ymin>
           <xmax>91</xmax>
           <ymax>567</ymax>
       </bndbox>
   </object>
   <object>
       <name>Roadline</name>
       <label_id>4</label_id>
       <bndbox>
           <xmin>57</xmin>
           <ymin>1053</ymin>
           <xmax>105</xmax>
           <ymax>1080</ymax>
       </bndbox>
   </object>
   <object>
       <name>Roadline</name>
       <label_id>4</label_id>
       <bndbox>
           <xmin>693</xmin>
           <ymin>743</ymin>
           <xmax>1077</xmax>
           <ymax>1080</ymax>
       </bndbox>
   </object>
</annotation>
