<annotation>
   <path>./data\Town04\rgb0\105.jpg</path>
   <bbox_num>3</bbox_num>
   <size>
       <width>1080</width>
       <height>1080</height>
       <depth>3</depth>
   </size>
   <object>
       <name>Roadline</name>
       <label_id>4</label_id>
       <bndbox>
           <xmin>0</xmin>
           <ymin>771</ymin>
           <xmax>229</xmax>
           <ymax>892</ymax>
       </bndbox>
   </object>
   <object>
       <name>Roadline</name>
       <label_id>4</label_id>
       <bndbox>
           <xmin>749</xmin>
           <ymin>759</ymin>
           <xmax>1068</xmax>
           <ymax>1080</ymax>
       </bndbox>
   </object>
   <object>
       <name>Roadline</name>
       <label_id>4</label_id>
       <bndbox>
           <xmin>40</xmin>
           <ymin>688</ymin>
           <xmax>406</xmax>
           <ymax>1080</ymax>
       </bndbox>
   </object>
</annotation>
