<annotation>
   <path>./data\Town04\rgb0\176.jpg</path>
   <bbox_num>5</bbox_num>
   <size>
       <width>1080</width>
       <height>1080</height>
       <depth>3</depth>
   </size>
   <object>
       <name>TrafficLight</name>
       <label_id>0</label_id>
       <bndbox>
           <xmin>523</xmin>
           <ymin>401</ymin>
           <xmax>529</xmax>
           <ymax>425</ymax>
       </bndbox>
   </object>
   <object>
       <name>Roadline</name>
       <label_id>4</label_id>
       <bndbox>
           <xmin>977</xmin>
           <ymin>717</ymin>
           <xmax>1080</xmax>
           <ymax>733</ymax>
       </bndbox>
   </object>
   <object>
       <name>Roadline</name>
       <label_id>4</label_id>
       <bndbox>
           <xmin>913</xmin>
           <ymin>691</ymin>
           <xmax>1080</xmax>
           <ymax>701</ymax>
       </bndbox>
   </object>
   <object>
       <name>Roadline</name>
       <label_id>4</label_id>
       <bndbox>
           <xmin>863</xmin>
           <ymin>671</ymin>
           <xmax>1026</xmax>
           <ymax>679</ymax>
       </bndbox>
   </object>
   <object>
       <name>Roadline</name>
       <label_id>4</label_id>
       <bndbox>
           <xmin>823</xmin>
           <ymin>657</ymin>
           <xmax>973</xmax>
           <ymax>661</ymax>
       </bndbox>
   </object>
</annotation>
