<annotation>
   <path>./data\Town04\rgb0\66.jpg</path>
   <bbox_num>5</bbox_num>
   <size>
       <width>1080</width>
       <height>1080</height>
       <depth>3</depth>
   </size>
   <object>
       <name>TrafficSign</name>
       <label_id>1</label_id>
       <bndbox>
           <xmin>665</xmin>
           <ymin>535</ymin>
           <xmax>681</xmax>
           <ymax>549</ymax>
       </bndbox>
   </object>
   <object>
       <name>TrafficSign</name>
       <label_id>1</label_id>
       <bndbox>
           <xmin>503</xmin>
           <ymin>527</ymin>
           <xmax>533</xmax>
           <ymax>557</ymax>
       </bndbox>
   </object>
   <object>
       <name>Vehicle</name>
       <label_id>2</label_id>
       <bndbox>
           <xmin>381</xmin>
           <ymin>559</ymin>
           <xmax>465</xmax>
           <ymax>607</ymax>
       </bndbox>
   </object>
   <object>
       <name>Roadline</name>
       <label_id>4</label_id>
       <bndbox>
           <xmin>911</xmin>
           <ymin>707</ymin>
           <xmax>1080</xmax>
           <ymax>1018</ymax>
       </bndbox>
   </object>
   <object>
       <name>Roadline</name>
       <label_id>4</label_id>
       <bndbox>
           <xmin>29</xmin>
           <ymin>703</ymin>
           <xmax>391</xmax>
           <ymax>1080</ymax>
       </bndbox>
   </object>
</annotation>
