<annotation>
   <path>./data\Town04\rgb0\708.jpg</path>
   <bbox_num>8</bbox_num>
   <size>
       <width>1080</width>
       <height>1080</height>
       <depth>3</depth>
   </size>
   <object>
       <name>TrafficLight</name>
       <label_id>0</label_id>
       <bndbox>
           <xmin>467</xmin>
           <ymin>0</ymin>
           <xmax>499</xmax>
           <ymax>87</ymax>
       </bndbox>
   </object>
   <object>
       <name>Vehicle</name>
       <label_id>2</label_id>
       <bndbox>
           <xmin>517</xmin>
           <ymin>557</ymin>
           <xmax>573</xmax>
           <ymax>601</ymax>
       </bndbox>
   </object>
   <object>
       <name>Vehicle</name>
       <label_id>2</label_id>
       <bndbox>
           <xmin>737</xmin>
           <ymin>549</ymin>
           <xmax>833</xmax>
           <ymax>597</ymax>
       </bndbox>
   </object>
   <object>
       <name>Roadline</name>
       <label_id>4</label_id>
       <bndbox>
           <xmin>817</xmin>
           <ymin>885</ymin>
           <xmax>1080</xmax>
           <ymax>1080</ymax>
       </bndbox>
   </object>
   <object>
       <name>Roadline</name>
       <label_id>4</label_id>
       <bndbox>
           <xmin>627</xmin>
           <ymin>883</ymin>
           <xmax>807</xmax>
           <ymax>1080</ymax>
       </bndbox>
   </object>
   <object>
       <name>Roadline</name>
       <label_id>4</label_id>
       <bndbox>
           <xmin>375</xmin>
           <ymin>881</ymin>
           <xmax>525</xmax>
           <ymax>1080</ymax>
       </bndbox>
   </object>
   <object>
       <name>Roadline</name>
       <label_id>4</label_id>
       <bndbox>
           <xmin>81</xmin>
           <ymin>879</ymin>
           <xmax>339</xmax>
           <ymax>1080</ymax>
       </bndbox>
   </object>
   <object>
       <name>Roadline</name>
       <label_id>4</label_id>
       <bndbox>
           <xmin>0</xmin>
           <ymin>877</ymin>
           <xmax>155</xmax>
           <ymax>1012</ymax>
       </bndbox>
   </object>
</annotation>
